wl/__init__.py
wl/db.py
wl/errors.py
wl/realtime.py
wl/routing.py
wl/utils.py
wl/wl.py
wl/models/__init__.py
wl/models/db.py
wl/models/general.py
wl/models/realtime.py
wl/models/routing.py
wl-0.1.2.dist-info/DESCRIPTION.rst
wl-0.1.2.dist-info/METADATA
wl-0.1.2.dist-info/RECORD
wl-0.1.2.dist-info/WHEEL
wl-0.1.2.dist-info/metadata.json
wl-0.1.2.dist-info/top_level.txt
