Metadata-Version: 2.0
Name: wl
Version: 0.1.2
Summary: UNKNOWN
Home-page: https://github.com/the01/python-wienerlinien
Author: the01
Author-email: jungflor@gmail.com
License: MIT License
Platform: UNKNOWN
Classifier: Development Status :: 4 - Beta
Classifier: Intended Audience :: Developers
Classifier: License :: OSI Approved :: MIT License
Classifier: Natural Language :: English
Classifier: Programming Language :: Python :: 2
Classifier: Programming Language :: Python :: 2.7
Requires-Dist: flotils (<0.5,>=0.4)
Requires-Dist: floscraper (<0.3,>=0.2.1)
Requires-Dist: requests (<3.0,>=2.18)
